aip/__init__.py
aip/board.py
aip/build.py
aip/command.py
aip/flash.py
aip/install.py
aip/list.py
aip/logger.py
aip/main.py
aip/parser.py
aip/shell.py
aip/uninstall.py
aip/utils.py
aip/variable.py
ardupy_aip-1.0.0.data/scripts/ardupy-aip
ardupy_aip-1.0.0.dist-info/LICENSE
ardupy_aip-1.0.0.dist-info/METADATA
ardupy_aip-1.0.0.dist-info/WHEEL
ardupy_aip-1.0.0.dist-info/entry_points.txt
ardupy_aip-1.0.0.dist-info/top_level.txt
ardupy_aip-1.0.0.dist-info/RECORD
