Metadata-Version: 2.1
Name: ardupy-aip
Version: 1.0.0
Summary: ArduPy Integrated Platform
Home-page: https://github.com/seeed-studio/ardupy-aip
Author: Baozhu Zuo
Author-email: zuobaozhu@gmail.com
License: MIT License
Keywords: voice doa beamforming kws
Platform: UNKNOWN
Classifier: Development Status :: 5 - Production/Stable
Classifier: Intended Audience :: Developers
Classifier: License :: OSI Approved :: MIT License
Classifier: Topic :: Software Development :: Build Tools
Classifier: Programming Language :: Python
Classifier: Programming Language :: Python :: 2
Classifier: Programming Language :: Python :: 2.7
Classifier: Programming Language :: Python :: 3
Classifier: Programming Language :: Python :: 3.5
Classifier: Programming Language :: Python :: 3.6
Classifier: Programming Language :: Python :: 3.7
Classifier: Programming Language :: Python :: 3.8
Classifier: Programming Language :: Python :: Implementation :: CPython
Classifier: Programming Language :: Python :: Implementation :: PyPy
Requires-Dist: pyusb
Requires-Dist: demjson
Requires-Dist: pyserial
Requires-Dist: colorama
Requires-Dist: ardupy-mpfshell
Requires-Dist: pip (>=20.1)
